setup.py
Bazinga.egg-info/PKG-INFO
Bazinga.egg-info/SOURCES.txt
Bazinga.egg-info/dependency_links.txt
Bazinga.egg-info/entry_points.txt
Bazinga.egg-info/requires.txt
Bazinga.egg-info/top_level.txt
bazinga/__init__.py